[{"color": [189, 212, 161], "title": "1 Floresta"}, {"color": [255, 255, 255], "title": "2 Hidrografia"}, {"color": [255, 235, 190], "title": "3 Nao Floresta"}, {"color": [255, 235, 190], "title": "4 Nao Floresta2"}, {"color": [178, 178, 178], "title": "6 d2007"}, {"color": [178, 178, 178], "title": "7 d2008"}, {"color": [178, 178, 178], "title": "8 d2009"}, {"color": [178, 178, 178], "title": "9 d2010"}, {"color": [178, 178, 178], "title": "10 d2011"}, {"color": [178, 178, 178], "title": "11 d2012"}, {"color": [178, 178, 178], "title": "12 d2013"}, {"color": [178, 178, 178], "title": "13 d2014"}, {"color": [178, 178, 178], "title": "14 d2015"}, {"color": [178, 178, 178], "title": "15 d2016"}, {"color": [178, 178, 178], "title": "16 d2017"}, {"color": [178, 178, 178], "title": "17 d2018"}, {"color": [130, 27, 121], "title": "18 r2010"}, {"color": [175, 232, 142], "title": "19 r2011"}, {"color": [127, 92, 242], "title": "20 r2012"}, {"color": [22, 224, 130], "title": "21 r2013"}, {"color": [150, 131, 132], "title": "22 r2014"}, {"color": [115, 74, 117], "title": "23 r2015"}, {"color": [51, 77, 20], "title": "24 r2016"}, {"color": [24, 42, 122], "title": "25 r2017"}, {"color": [8, 55, 84], "title": "26 r2018"}, {"color": [178, 178, 178], "title": "27 d2019"}, {"color": [162, 173, 38], "title": "28 r2019"}, {"color": [178, 178, 178], "title": "29 d2020"}, {"color": [196, 189, 252], "title": "30 Nuvem"}]